extliner/__init__.py
extliner/cli.py
extliner/main.py
extliner-0.0.10.dist-info/entry_points.txt
extliner-0.0.10.dist-info/licenses/LICENSE
extliner-0.0.10.dist-info/WHEEL
extliner-0.0.10.dist-info/METADATA
extliner-0.0.10.dist-info/RECORD
