Metadata-Version: 2.4
Name: extliner
Version: 0.0.10
Summary: A simple command-line tool to count lines in files by extension.
Keywords: line count,file analysis,command line tool,file extension,python,CLI,file processing
Author-email: Deepak Raj <deepak008@live.com>
Requires-Python: >=3.6
Classifier: Development Status :: 5 - Production/Stable
Classifier: Programming Language :: Python :: 3
Classifier: Operating System :: OS Independent
Classifier: Intended Audience :: Developers
License-File: LICENSE
Requires-Dist: tabulate>=0.9.0
Requires-Dist: tqdm>=4.67.1
Project-URL: Documentation, https://extliner.readthedocs.io/en/latest/
Project-URL: Source, https://github.com/codeperfectplus/extliner
Project-URL: Tracker, https://github.com/codeperfectplus/extliner/issues
